agudelo_shared_services/__init__.py
agudelo_shared_services/_version.py
agudelo_shared_services/app.py
agudelo_shared_services/db.py
agudelo_shared_services/blueprints/api.py
agudelo_shared_services/exceptions/__init__.py
agudelo_shared_services/exceptions/server_unsupported_env_error.py
agudelo_shared_services/models/__init__.py
agudelo_shared_services/models/invoice.py
agudelo_shared_services/namespaces/invoices.py
agudelo_shared_services-0.1.dev1.dist-info/METADATA
agudelo_shared_services-0.1.dev1.dist-info/WHEEL
agudelo_shared_services-0.1.dev1.dist-info/entry_points.txt
agudelo_shared_services-0.1.dev1.dist-info/top_level.txt
agudelo_shared_services-0.1.dev1.dist-info/RECORD
