Metadata-Version: 2.4
Name: agudelo_shared_services
Version: 0.1.dev1
Summary: Agudelos Family Set of shared utilities
Author-email: Juan Esteban Agudelo Agudelo <juan@agudelo.com.co>
License-Expression: MIT AND (Apache-2.0 OR BSD-2-Clause)
Keywords: Familia,Compartido,Servicios
Classifier: Development Status :: 4 - Beta
Classifier: Environment :: Web Environment
Classifier: Framework :: Flask
Classifier: Framework :: Pytest
Classifier: Programming Language :: Python :: 3.10
Classifier: Programming Language :: Python :: 3.11
Classifier: Programming Language :: Python :: 3.12
Classifier: Programming Language :: Python :: Implementation :: CPython
Classifier: Programming Language :: Python :: Implementation :: PyPy
Requires-Python: >=3.10
Requires-Dist: flask
Requires-Dist: flask-restx
Requires-Dist: asgiref
Requires-Dist: hypercorn
Requires-Dist: hypercorn[h3]
Requires-Dist: sqlalchemy
